envoy_protobuf/__init__.py
envoy_protobuf/builder.py
envoy_protobuf/main.py
envoy_protobuf/models.py
envoy_protobuf/util.py
python_envoy_protobuf_installer-0.1.0.dist-info/AUTHORS.rst
python_envoy_protobuf_installer-0.1.0.dist-info/LICENSE
python_envoy_protobuf_installer-0.1.0.dist-info/METADATA
python_envoy_protobuf_installer-0.1.0.dist-info/WHEEL
python_envoy_protobuf_installer-0.1.0.dist-info/entry_points.txt
python_envoy_protobuf_installer-0.1.0.dist-info/top_level.txt
python_envoy_protobuf_installer-0.1.0.dist-info/RECORD
