Metadata-Version: 2.1
Name: python-envoy-protobuf-installer
Version: 0.1.0
Summary: Installer for Envoy Protobuf files
Home-page: https://github.com/dpetzold/envoy_protobuf
Author: Derrick Petzold
Author-email: github@petzold.io
License: UNKNOWN
Keywords: envoy_protobuf
Platform: UNKNOWN
Classifier: Development Status :: 2 - Pre-Alpha
Classifier: Intended Audience :: Developers
Classifier: Natural Language :: English
Classifier: Programming Language :: Python :: 3
Classifier: Programming Language :: Python :: 3.8
Requires-Python: >=3.8
Requires-Dist: protobuf-gen (==0.0.4)
Provides-Extra: dev
Requires-Dist: bump2version ; extra == 'dev'
Requires-Dist: bpython ; extra == 'dev'
Requires-Dist: flake8 ; extra == 'dev'
Requires-Dist: pre-commit ; extra == 'dev'
Requires-Dist: twine ; extra == 'dev'
Requires-Dist: wheel ; extra == 'dev'
Requires-Dist: pytest ; extra == 'dev'
Requires-Dist: pytest-cov ; extra == 'dev'
Requires-Dist: pytest-socket ; extra == 'dev'
Requires-Dist: python-coveralls ; extra == 'dev'
